[
    {
        "username": "artlover92",
        "platform": "TikTok",
        "text": "Anyone doing portrait commissions?",
        "timestamp": "2025-12-06T07:58:58.897781",
        "score": 1.0,
        "ai_reply": "Hi there! Thanks for reaching out! I specialize in surreal and abstract art, but I\u2019d be happy to chat about creating a unique portrait for you! Let me know what you have in mind, and we can explore some creative options together. Looking forward to hearing from you!",
        "status": "pending",
        "saved_at": "2025-12-06T07:59:03.827260"
    },
    {
        "username": "artlover92",
        "platform": "TikTok",
        "text": "Anyone doing portrait commissions?",
        "timestamp": "2025-12-06T07:59:11.831037",
        "score": 1.0,
        "ai_reply": "Hi there! Thanks for reaching out! I\u2019m actually focused on surreal and abstract art, but I can help you explore unique interpretations of portraits if that interests you. Let me know your vision, and we can create something truly special together! ",
        "status": "pending",
        "saved_at": "2025-12-06T07:59:15.075704"
    },
    {
        "username": "creativehunter",
        "platform": "Instagram",
        "text": "Looking for an artist to draw my dog!",
        "timestamp": "2025-12-06T07:59:17.077523",
        "score": 0.6,
        "ai_reply": "Hi there! Thanks for reaching out! I\u2019d love to help bring your dog to life in a surreal and abstract way. Let\u2019s chat about what you have in mind\u2014any specific ideas or styles you\u2019re thinking of? Looking forward to hearing from you! \ud83d\udc3e\u2728",
        "status": "pending",
        "saved_at": "2025-12-06T07:59:19.375611"
    },
    {
        "username": "visualvibes",
        "platform": "TikTok",
        "text": "Need a surreal painting for my apartment.",
        "timestamp": "2025-12-06T07:59:21.377430",
        "score": 0.6,
        "ai_reply": "Hi there! Thanks for reaching out! I'd love to help bring your vision to life. Could you share a bit more about what you\u2019re looking for? Any specific themes, colors, or emotions you\u2019d like the piece to convey? Looking forward to collaborating with you!",
        "status": "pending",
        "saved_at": "2025-12-06T07:59:23.699540"
    },
    {
        "username": "visualvibes",
        "platform": "TikTok",
        "text": "Need a surreal painting for my apartment.",
        "timestamp": "2025-12-06T07:59:25.700863",
        "score": 0.6,
        "ai_reply": "Hi there!\n\nThanks for reaching out! I\u2019d love to help you create a surreal painting for your apartment. Do you have any specific themes or colors in mind? Let\u2019s make something truly unique together!\n\nLooking forward to hearing from you!\n\nBest,  \nJoe Fleishman\u2019s AI Art Assistant",
        "status": "pending",
        "saved_at": "2025-12-06T07:59:28.959824"
    },
    {
        "username": "creativehunter",
        "platform": "Instagram",
        "text": "Looking for an artist to draw my dog!",
        "timestamp": "2025-12-06T07:59:30.961643",
        "score": 0.6,
        "ai_reply": "Hi there! Thank you for reaching out! I\u2019d love to help bring your dog to life in a unique and abstract way. Could you share a bit more about your dog\u2019s personality and any specific ideas you have in mind? Looking forward to creating something special together!",
        "status": "pending",
        "saved_at": "2025-12-06T07:59:33.701132"
    },
    {
        "username": "visualvibes",
        "platform": "TikTok",
        "text": "Need a surreal painting for my apartment.",
        "timestamp": "2025-12-06T07:59:45.707080",
        "score": 0.6,
        "ai_reply": "Hi there!\n\nThanks for reaching out! I\u2019d love to help you find the perfect surreal painting for your apartment. Do you have any specific themes or colors in mind that resonate with you? Looking forward to creating something unique together!\n\nBest,  \nJoe Fleishman\u2019s AI Art Assistant",
        "status": "pending",
        "saved_at": "2025-12-06T07:59:48.693794"
    },
    {
        "username": "artlover92",
        "platform": "TikTok",
        "text": "Anyone doing portrait commissions?",
        "timestamp": "2025-12-06T07:59:50.694611",
        "score": 1.0,
        "ai_reply": "Hi there! Thanks for reaching out! While I primarily focus on surreal and abstract art, I'd love to chat about what you have in mind for a portrait. Let's see if we can create something truly unique together! Feel free to share your ideas! \ud83d\ude0a",
        "status": "pending",
        "saved_at": "2025-12-06T07:59:53.021726"
    },
    {
        "username": "artlover92",
        "platform": "TikTok",
        "text": "Anyone doing portrait commissions?",
        "timestamp": "2025-12-06T07:59:55.023560",
        "score": 1.0,
        "ai_reply": "Hi there! Thanks for reaching out! Joe doesn\u2019t typically focus on traditional portraits, but he loves exploring unique, abstract interpretations of subjects. If you're interested in a surreal twist on a portrait, we'd love to discuss your ideas! Let us know what you have in mind! \ud83d\ude0a",
        "status": "pending",
        "saved_at": "2025-12-06T07:59:57.304132"
    },
    {
        "username": "visualvibes",
        "platform": "TikTok",
        "text": "Need a surreal painting for my apartment.",
        "timestamp": "2025-12-06T07:59:59.305951",
        "score": 0.6,
        "ai_reply": "Hi there!\n\nThanks for reaching out! I'd love to help you create a surreal painting that will bring your apartment to life. Do you have any specific themes or colors in mind? Let\u2019s make something truly unique together!\n\nBest,  \nJoe Fleishman\u2019s AI Art Assistant",
        "status": "pending",
        "saved_at": "2025-12-06T08:00:01.624058"
    },
    {
        "username": "artlover92",
        "platform": "TikTok",
        "text": "Anyone doing portrait commissions?",
        "timestamp": "2025-12-06T08:00:05.627199",
        "score": 1.0,
        "ai_reply": "Hi there! \ud83d\ude0a Yes, Joe Fleishman is currently accepting portrait commissions. His unique style brings a surreal touch to traditional portraiture. If you're interested, feel free to share more about your vision, and we can discuss it further! Looking forward to hearing from you! \ud83c\udfa8\u2728",
        "status": "pending",
        "saved_at": "2025-12-06T08:00:07.962321"
    },
    {
        "username": "artlover92",
        "platform": "TikTok",
        "text": "Anyone doing portrait commissions?",
        "timestamp": "2025-12-06T08:00:15.966097",
        "score": 1.0,
        "ai_reply": "Hi there! Thanks for reaching out! While I typically focus on surreal and abstract art, I\u2019d love to chat about your vision. We might be able to create something uniquely inspired by a portrait! Let me know what you have in mind! \ud83d\ude0a",
        "status": "pending",
        "saved_at": "2025-12-06T08:00:18.336251"
    },
    {
        "username": "creativehunter",
        "platform": "Instagram",
        "text": "Looking for an artist to draw my dog!",
        "timestamp": "2025-12-06T08:00:20.338070",
        "score": 0.6,
        "ai_reply": "Hi there!\n\nThanks for reaching out! I\u2019d love to help bring your dog to life in a surreal or abstract style. Could you share a bit more about your pup and any specific ideas you have in mind? Looking forward to creating something special together!\n\nBest,  \nJoe",
        "status": "pending",
        "saved_at": "2025-12-06T08:00:23.289752"
    },
    {
        "username": "creativehunter",
        "platform": "Instagram",
        "text": "Looking for an artist to draw my dog!",
        "timestamp": "2025-12-06T08:00:27.292894",
        "score": 0.6,
        "ai_reply": "Hi there!\n\nThanks for reaching out! I'd love to help capture your dog's unique personality in a surreal and abstract style. Could you share a bit more about your pup and what you have in mind? Looking forward to collaborating with you!\n\nBest,  \nJoe",
        "status": "pending",
        "saved_at": "2025-12-06T08:00:29.702083"
    },
    {
        "username": "artlover92",
        "platform": "TikTok",
        "text": "Anyone doing portrait commissions?",
        "timestamp": "2025-12-06T08:00:33.704720",
        "score": 1.0,
        "ai_reply": "Hi there! Thanks for reaching out! Joe is currently focused on his surreal and abstract pieces, but he loves the idea of exploring portraits in a unique way. If you're open to an artistic twist, we'd love to discuss how he can bring your vision to life! Let us know what you have in mind! \ud83d\ude0a\ud83c\udfa8",
        "status": "pending",
        "saved_at": "2025-12-06T08:00:36.181970"
    },
    {
        "username": "visualvibes",
        "platform": "TikTok",
        "text": "Need a surreal painting for my apartment.",
        "timestamp": "2025-12-06T08:00:42.184929",
        "score": 0.6,
        "ai_reply": "Hi there! Thanks for reaching out! I'd love to help you find the perfect surreal painting for your apartment. Do you have any themes or colors in mind that resonate with you? Let\u2019s create something amazing together!",
        "status": "pending",
        "saved_at": "2025-12-06T08:00:44.574100"
    },
    {
        "username": "visualvibes",
        "platform": "TikTok",
        "text": "Need a surreal painting for my apartment.",
        "timestamp": "2025-12-06T08:00:46.575919",
        "score": 0.6,
        "ai_reply": "Hi there! Thanks for reaching out! I'd love to help you create a surreal painting that perfectly complements your apartment. Do you have any specific themes or colors in mind? Let's make something unique together!",
        "status": "pending",
        "saved_at": "2025-12-06T08:00:49.041474"
    },
    {
        "username": "visualvibes",
        "platform": "TikTok",
        "text": "Need a surreal painting for my apartment.",
        "timestamp": "2025-12-06T08:00:53.044111",
        "score": 0.6,
        "ai_reply": "Hi there! Thanks for reaching out! I\u2019d love to help you create a surreal painting for your apartment. Do you have any specific themes or colors in mind? Let\u2019s make something unique that reflects your vision! Looking forward to hearing your ideas.",
        "status": "pending",
        "saved_at": "2025-12-06T08:00:55.359215"
    },
    {
        "username": "visualvibes",
        "platform": "TikTok",
        "text": "Need a surreal painting for my apartment.",
        "timestamp": "2025-12-06T08:00:57.361033",
        "score": 0.6,
        "ai_reply": "Hi there!\n\nThanks for reaching out! I\u2019d love to help you find the perfect surreal painting for your apartment. Do you have any specific themes, colors, or feelings in mind that you'd like to explore? Let\u2019s create something unique together!\n\nBest,  \nJoe",
        "status": "pending",
        "saved_at": "2025-12-06T08:00:59.679644"
    },
    {
        "username": "creativehunter",
        "platform": "Instagram",
        "text": "Looking for an artist to draw my dog!",
        "timestamp": "2025-12-06T08:01:01.681463",
        "score": 0.6,
        "ai_reply": "Hi there!\n\nThanks for reaching out! I\u2019d love to help capture the essence of your dog through art. Could you share a bit more about your furry friend? Any specific style or vibe you\u2019re looking for? \n\nLooking forward to hearing from you!\n\nBest,  \nJoe",
        "status": "pending",
        "saved_at": "2025-12-06T08:01:04.100661"
    },
    {
        "username": "creativehunter",
        "platform": "Instagram",
        "text": "Looking for an artist to draw my dog!",
        "timestamp": "2025-12-06T08:01:06.102480",
        "score": 0.6,
        "ai_reply": "Hi there! Thanks for reaching out! I'd love to help capture the essence of your dog in a unique way. My style leans towards surreal and abstract, so we can create something truly imaginative! If you\u2019d like, we can chat about your vision and how we can bring it to life. Looking forward to hearing more! \ud83d\udc3e\u2728",
        "status": "pending",
        "saved_at": "2025-12-06T08:01:08.679326"
    },
    {
        "username": "creativehunter",
        "platform": "Instagram",
        "text": "Looking for an artist to draw my dog!",
        "timestamp": "2025-12-06T08:01:14.682781",
        "score": 0.6,
        "ai_reply": "Hi there! Thanks for reaching out! While I specialize in surreal and abstract art, I'd love to help you capture the essence of your dog in a unique way. If you're open to a creative twist, I can create something whimsical and imaginative that reflects your furry friend's personality. Let me know what you think! \ud83d\udc3e\ud83c\udfa8",
        "status": "pending",
        "saved_at": "2025-12-06T08:01:17.197065"
    },
    {
        "username": "creativehunter",
        "platform": "Instagram",
        "text": "Looking for an artist to draw my dog!",
        "timestamp": "2025-12-06T08:01:19.198440",
        "score": 0.6,
        "ai_reply": "Hi there!\n\nThanks for reaching out! I\u2019d love to help capture the essence of your dog in a unique, surreal way. Could you share a bit more about your pup\u2019s personality or any specific ideas you have in mind? Looking forward to hearing from you!\n\nBest,  \nJoe",
        "status": "pending",
        "saved_at": "2025-12-06T08:01:21.675691"
    },
    {
        "username": "artlover92",
        "platform": "TikTok",
        "text": "Anyone doing portrait commissions?",
        "timestamp": "2025-12-06T08:01:25.678328",
        "score": 1.0,
        "ai_reply": "Hi there! Thanks for reaching out! While I don\u2019t typically focus on traditional portraits, I\u2019d love to explore surreal and abstract interpretations if you're open to that. Let me know your ideas, and we can create something truly unique together! Looking forward to hearing from you! \ud83d\ude0a",
        "status": "pending",
        "saved_at": "2025-12-06T08:01:27.971412"
    },
    {
        "username": "creativehunter",
        "platform": "Instagram",
        "text": "Looking for an artist to draw my dog!",
        "timestamp": "2025-12-06T08:01:29.973735",
        "score": 0.6,
        "ai_reply": "Hi there! Thanks for reaching out! I'd love to help bring your dog's personality to life in a unique way. If you have any specific ideas or themes in mind, feel free to share! Looking forward to hearing more about your furry friend! \ud83d\udc3e\u2728",
        "status": "pending",
        "saved_at": "2025-12-06T08:01:32.297847"
    },
    {
        "username": "visualvibes",
        "platform": "TikTok",
        "text": "Need a surreal painting for my apartment.",
        "timestamp": "2025-12-06T08:01:34.299665",
        "score": 0.6,
        "ai_reply": "Hi there!\n\nThanks for reaching out! I\u2019d love to help you with a surreal painting for your apartment. Do you have any specific themes or colors in mind that resonate with you? Let\u2019s create something unique together!\n\nLooking forward to hearing from you!\n\nBest,  \nJoe Fleishman\u2019s AI Art Assistant",
        "status": "pending",
        "saved_at": "2025-12-06T08:01:36.689837"
    },
    {
        "username": "visualvibes",
        "platform": "TikTok",
        "text": "Need a surreal painting for my apartment.",
        "timestamp": "2025-12-06T08:01:38.691656",
        "score": 0.6,
        "ai_reply": "Hi there! Thanks for reaching out! I\u2019d love to help you find the perfect surreal painting for your apartment. Do you have any specific themes or colors in mind? Looking forward to chatting more!",
        "status": "pending",
        "saved_at": "2025-12-06T08:01:41.097346"
    },
    {
        "username": "visualvibes",
        "platform": "TikTok",
        "text": "Need a surreal painting for my apartment.",
        "timestamp": "2025-12-06T08:01:43.099165",
        "score": 0.6,
        "ai_reply": "Hi there! Thanks for reaching out! I'd love to help you create a surreal painting for your apartment. What kind of vibes or themes are you looking for? Feel free to share any ideas or inspirations you have in mind! Looking forward to collaborating with you! \ud83c\udf1f",
        "status": "pending",
        "saved_at": "2025-12-06T08:01:45.347208"
    },
    {
        "username": "creativehunter",
        "platform": "Instagram",
        "text": "Looking for an artist to draw my dog!",
        "timestamp": "2025-12-06T08:01:47.350027",
        "score": 0.6,
        "ai_reply": "Hi there! Thanks for reaching out! I\u2019d love to help you capture the essence of your dog in a unique and artistic way. Could you share a bit more about your dog\u2019s personality or any specific style you have in mind? Looking forward to hearing from you!",
        "status": "pending",
        "saved_at": "2025-12-06T08:01:49.784240"
    },
    {
        "username": "visualvibes",
        "platform": "TikTok",
        "text": "Need a surreal painting for my apartment.",
        "timestamp": "2025-12-06T08:01:51.785562",
        "score": 0.6,
        "ai_reply": "Hi there! That sounds exciting! I\u2019d love to help you create a surreal painting that perfectly complements your apartment. Do you have any specific themes or colors in mind? Let\u2019s bring your vision to life! \ud83d\ude0a\ud83c\udfa8",
        "status": "pending",
        "saved_at": "2025-12-06T08:01:54.212767"
    },
    {
        "username": "artlover92",
        "platform": "TikTok",
        "text": "Anyone doing portrait commissions?",
        "timestamp": "2025-12-06T08:01:56.214095",
        "score": 1.0,
        "ai_reply": "Hi there! Thanks for reaching out! While I focus more on surreal and abstract art, I'd love to help you create something unique. If you\u2019re interested in a stylized or abstract take on a portrait, let me know! I\u2019d be happy to discuss ideas with you. \ud83d\ude0a",
        "status": "pending",
        "saved_at": "2025-12-06T08:01:58.619275"
    },
    {
        "username": "visualvibes",
        "platform": "TikTok",
        "text": "Need a surreal painting for my apartment.",
        "timestamp": "2025-12-06T08:02:02.621921",
        "score": 0.6,
        "ai_reply": "Hi there! Thanks for reaching out! I\u2019d love to help you find the perfect surreal painting for your apartment. Do you have any themes or colors in mind that you\u2019d like to explore? Looking forward to collaborating with you!",
        "status": "pending",
        "saved_at": "2025-12-06T08:02:05.249309"
    },
    {
        "username": "creativehunter",
        "platform": "Instagram",
        "text": "Looking for an artist to draw my dog!",
        "timestamp": "2025-12-06T08:02:07.251128",
        "score": 0.6,
        "ai_reply": "Hi there! Thanks for reaching out! I\u2019d love to help bring your dog to life through art. My style tends to be a bit surreal and abstract, which can create a unique take on your pet. If you\u2019re open to that, let\u2019s chat more about what you have in mind! \ud83d\udc36\u2728",
        "status": "pending",
        "saved_at": "2025-12-06T08:02:09.554220"
    },
    {
        "username": "artlover92",
        "platform": "TikTok",
        "text": "Anyone doing portrait commissions?",
        "timestamp": "2025-12-06T08:02:13.557361",
        "score": 1.0,
        "ai_reply": "Hi there! Thanks for reaching out! While I specialize in surreal and abstract art, Joe doesn\u2019t typically focus on traditional portraits. However, if you\u2019re open to a unique twist on a portrait or something imaginative, he\u2019d love to explore that with you! Let me know what you have in mind! \ud83d\ude0a",
        "status": "pending",
        "saved_at": "2025-12-06T08:02:16.013593"
    },
    {
        "username": "visualvibes",
        "platform": "TikTok",
        "text": "Need a surreal painting for my apartment.",
        "timestamp": "2025-12-06T08:02:18.015412",
        "score": 0.6,
        "ai_reply": "Hi there! Thanks for reaching out! I\u2019d love to help create a surreal painting that complements your apartment. Do you have any specific themes or colors in mind? Let\u2019s make something special together!",
        "status": "pending",
        "saved_at": "2025-12-06T08:02:20.293986"
    },
    {
        "username": "visualvibes",
        "platform": "TikTok",
        "text": "Need a surreal painting for my apartment.",
        "timestamp": "2025-12-06T08:02:26.297441",
        "score": 0.6,
        "ai_reply": "Hi there! Thanks for reaching out! I'd love to help you create a unique surreal painting for your apartment. Do you have any specific themes or colors in mind? Looking forward to hearing more about your vision!",
        "status": "pending",
        "saved_at": "2025-12-06T08:02:28.762681"
    },
    {
        "username": "artlover92",
        "platform": "TikTok",
        "text": "Anyone doing portrait commissions?",
        "timestamp": "2025-12-06T08:02:32.765823",
        "score": 1.0,
        "ai_reply": "Hi there! Thanks for reaching out! I don't typically focus on traditional portraits, but I love creating surreal and abstract pieces that convey unique emotions and stories. If you\u2019re interested in something along those lines, I\u2019d be thrilled to collaborate! Let me know your thoughts! ",
        "status": "pending",
        "saved_at": "2025-12-06T08:02:35.157997"
    },
    {
        "username": "artlover92",
        "platform": "TikTok",
        "text": "Anyone doing portrait commissions?",
        "timestamp": "2025-12-06T08:02:41.162016",
        "score": 1.0,
        "ai_reply": "Hi there! Thanks for reaching out! I don't specialize in traditional portrait commissions, but I\u2019d love to explore creating an abstract interpretation of a portrait if that interests you. Let me know what you have in mind! Looking forward to hearing from you!",
        "status": "pending",
        "saved_at": "2025-12-06T08:02:44.232310"
    },
    {
        "username": "visualvibes",
        "platform": "TikTok",
        "text": "Need a surreal painting for my apartment.",
        "timestamp": "2025-12-06T08:02:46.234128",
        "score": 0.6,
        "ai_reply": "Hi there! Thanks for reaching out. I\u2019d love to help you create a unique surreal painting for your apartment. Do you have any themes or colors in mind that resonate with you? Let\u2019s bring your vision to life!",
        "status": "pending",
        "saved_at": "2025-12-06T08:02:48.617839"
    },
    {
        "username": "visualvibes",
        "platform": "TikTok",
        "text": "Need a surreal painting for my apartment.",
        "timestamp": "2025-12-06T08:02:56.623634",
        "score": 0.6,
        "ai_reply": "Hi there!\n\nThanks for reaching out! I\u2019d love to help you find the perfect surreal painting for your apartment. Could you share a bit about the vibe you\u2019re going for or any specific elements you'd like to include? Looking forward to collaborating with you!\n\nBest,  \nJoe Fleishman\u2019s AI Art Assistant",
        "status": "pending",
        "saved_at": "2025-12-06T08:02:59.079370"
    },
    {
        "username": "artlover92",
        "platform": "TikTok",
        "text": "Anyone doing portrait commissions?",
        "timestamp": "2025-12-06T08:03:01.081189",
        "score": 1.0,
        "ai_reply": "Hi there! Thanks for reaching out! Joe specializes in surreal and abstract art, which gives portraits a unique twist. If you're open to exploring a creative interpretation, we\u2019d love to discuss your vision further. Let us know what you have in mind! \ud83d\ude0a",
        "status": "pending",
        "saved_at": "2025-12-06T08:03:03.533434"
    },
    {
        "username": "creativehunter",
        "platform": "Instagram",
        "text": "Looking for an artist to draw my dog!",
        "timestamp": "2025-12-06T08:03:07.536607",
        "score": 0.6,
        "ai_reply": "Hi there! Thank you for reaching out! I\u2019d love to help capture the essence of your dog in a unique and abstract way. Could you share more about your dog\u2019s personality or any specific ideas you have in mind? Looking forward to hearing from you! \ud83d\udc3e\u2728",
        "status": "pending",
        "saved_at": "2025-12-06T08:03:09.907762"
    },
    {
        "username": "visualvibes",
        "platform": "TikTok",
        "text": "Need a surreal painting for my apartment.",
        "timestamp": "2025-12-06T08:03:13.910911",
        "score": 0.6,
        "ai_reply": "Hi there!\n\nThanks for reaching out! I\u2019d love to help you create a surreal painting for your apartment. Do you have any specific themes or colors in mind? Let\u2019s make something truly unique for your space!\n\nLooking forward to hearing from you!\n\nBest,  \nJoe Fleishman\u2019s AI Art Assistant",
        "status": "pending",
        "saved_at": "2025-12-06T08:03:16.312093"
    },
    {
        "username": "creativehunter",
        "platform": "Instagram",
        "text": "Looking for an artist to draw my dog!",
        "timestamp": "2025-12-06T08:03:18.314912",
        "score": 0.6,
        "ai_reply": "Hi there! Thanks for reaching out! I\u2019d love to help you capture your dog's unique personality in a surreal or abstract style. Could you share a bit more about your dog and any ideas you have in mind? Looking forward to creating something special together! \ud83d\ude0a",
        "status": "pending",
        "saved_at": "2025-12-06T08:03:20.678060"
    },
    {
        "username": "visualvibes",
        "platform": "TikTok",
        "text": "Need a surreal painting for my apartment.",
        "timestamp": "2025-12-06T08:03:22.680896",
        "score": 0.6,
        "ai_reply": "Hi there!\n\nThanks for reaching out! I\u2019d love to help you find the perfect surreal painting for your apartment. Can you share a bit about your style or any themes you're drawn to? Looking forward to collaborating with you!\n\nBest,  \nJoe",
        "status": "pending",
        "saved_at": "2025-12-06T08:03:25.128639"
    },
    {
        "username": "creativehunter",
        "platform": "Instagram",
        "text": "Looking for an artist to draw my dog!",
        "timestamp": "2025-12-06T08:03:27.130962",
        "score": 0.6,
        "ai_reply": "Hi there! I\u2019d love to help capture the essence of your dog in a unique, abstract way. Each pet has their own personality, and I can bring that to life through my art. Do you have any specific ideas or colors in mind? Looking forward to chatting more! \ud83d\udc3e\u2728",
        "status": "pending",
        "saved_at": "2025-12-06T08:03:29.523136"
    },
    {
        "username": "creativehunter",
        "platform": "Instagram",
        "text": "Looking for an artist to draw my dog!",
        "timestamp": "2025-12-06T08:03:33.526315",
        "score": 0.6,
        "ai_reply": "Hi there! Thanks for reaching out! I'd love to help capture your dog's unique personality in a surreal or abstract style. Let me know a bit more about your pup\u2019s features and any ideas you have in mind. Looking forward to collaborating! \ud83d\udc3e\u2728",
        "status": "pending",
        "saved_at": "2025-12-06T08:03:35.867443"
    },
    {
        "username": "creativehunter",
        "platform": "Instagram",
        "text": "Looking for an artist to draw my dog!",
        "timestamp": "2025-12-06T08:03:39.870599",
        "score": 0.6,
        "ai_reply": "Hi there! \ud83c\udfa8 That sounds like a fun project! I\u2019d love to help bring your dog\u2019s unique personality to life in a surreal or abstract way. Could you share a bit more about your pup and any specific ideas you have in mind? Looking forward to hearing from you! \ud83d\udc3e\u2728",
        "status": "pending",
        "saved_at": "2025-12-06T08:03:42.206722"
    },
    {
        "username": "creativehunter",
        "platform": "Instagram",
        "text": "Looking for an artist to draw my dog!",
        "timestamp": "2025-12-06T08:03:46.210400",
        "score": 0.6,
        "ai_reply": "Hi there! Thanks for reaching out! I\u2019d love to help bring your dog to life through art. Could you share a bit more about your dog's personality or any specific ideas you have in mind? Looking forward to hearing from you!",
        "status": "pending",
        "saved_at": "2025-12-06T08:03:48.822339"
    },
    {
        "username": "visualvibes",
        "platform": "TikTok",
        "text": "Need a surreal painting for my apartment.",
        "timestamp": "2025-12-06T08:03:50.824158",
        "score": 0.6,
        "ai_reply": "Hi there! Thanks for reaching out! I\u2019d love to help you find the perfect surreal painting for your apartment. Do you have any specific themes or colors in mind? Let\u2019s create something unique together!",
        "status": "pending",
        "saved_at": "2025-12-06T08:03:53.133761"
    },
    {
        "username": "visualvibes",
        "platform": "TikTok",
        "text": "Need a surreal painting for my apartment.",
        "timestamp": "2025-12-06T08:03:57.137407",
        "score": 0.6,
        "ai_reply": "Hi there! Thanks for reaching out! I\u2019d love to help you create a surreal painting that transforms your apartment. Do you have any specific themes or colors in mind? Let\u2019s bring your vision to life! Looking forward to chatting more.",
        "status": "pending",
        "saved_at": "2025-12-06T08:03:59.577137"
    }
]